{
    "addon_version": "4.0.07", 
    "files": {
        "channels": [
            "animeyt", 
            "cuevana3pro", 
            "cuevana3video", 
            "dontorrents", 
            "hacktorrent", 
            "henaojara", 
            "kiriasian", 
            "monoschinos", 
            "novelas360", 
            "pelispanda", 
            "seriesantiguas", 
            "seriesbiblicas"
        ], 
        "modules": [
            "submnuteam"
        ], 
        "root dir": [
            "dominios", 
            "version"
        ]
    }, 
    "fix_version": 2, 
    "hash": "e53fc122a11122c128f216062d9ed74f"
}